voxelwise_tutorials/__init__.py
voxelwise_tutorials/delayer.py
voxelwise_tutorials/io.py
voxelwise_tutorials/progress_bar.py
voxelwise_tutorials/regression_toy.py
voxelwise_tutorials/utils.py
voxelwise_tutorials/viz.py
voxelwise_tutorials/wordnet.py
voxelwise_tutorials/tests/__init__.py
voxelwise_tutorials/tests/test_delayer.py
voxelwise_tutorials/tests/test_io.py
voxelwise_tutorials/tests/test_mappers.py
voxelwise_tutorials/tests/test_model.py
voxelwise_tutorials/tests/test_regression_toy.py
voxelwise_tutorials/tests/test_utils.py
voxelwise_tutorials-0.1.7.dist-info/LICENSE.md
voxelwise_tutorials-0.1.7.dist-info/METADATA
voxelwise_tutorials-0.1.7.dist-info/WHEEL
voxelwise_tutorials-0.1.7.dist-info/top_level.txt
voxelwise_tutorials-0.1.7.dist-info/RECORD
