Metadata-Version: 2.1
Name: voxelwise-tutorials
Version: 0.1.7
Summary: Tools and tutorials for voxelwise modeling
Home-page: UNKNOWN
Maintainer: Tom Dupre la Tour
Maintainer-email: tom.dupre-la-tour@m4x.org
License: BSD (3-clause)
Platform: UNKNOWN
License-File: LICENSE.md
Requires-Dist: datalad
Requires-Dist: h5py
Requires-Dist: himalaya
Requires-Dist: matplotlib
Requires-Dist: networkx
Requires-Dist: nltk
Requires-Dist: numpy
Requires-Dist: pycortex (>=1.2.4)
Requires-Dist: pydot
Requires-Dist: pymoten
Requires-Dist: scikit-learn (>=0.23)
Requires-Dist: scipy
Provides-Extra: docs
Requires-Dist: nbformat ; extra == 'docs'
Requires-Dist: numpydoc ; extra == 'docs'
Requires-Dist: sphinx ; extra == 'docs'
Requires-Dist: sphinx-gallery ; extra == 'docs'
Provides-Extra: github
Requires-Dist: pytest ; extra == 'github'
